print_btree/__init__.py
print_btree/helpers/classes.py
print_btree/helpers/string_helper.py
print_btree/helpers/tree_helper.py
print_btree-0.0.14.dist-info/METADATA
print_btree-0.0.14.dist-info/WHEEL
print_btree-0.0.14.dist-info/licenses/LICENSE
print_btree-0.0.14.dist-info/RECORD
