Metadata-Version: 2.4
Name: print_btree
Version: 0.0.14
Summary: A package that prints binary trees in terminal
Project-URL: Homepage, https://github.com/zlliu246/print_btree
Project-URL: Issues, https://github.com/zlliu246/print_btree/issues
Author-email: Liu Zuo Lin <zlliu246@gmail.com>
License-File: LICENSE
Classifier: License :: OSI Approved :: MIT License
Classifier: Operating System :: OS Independent
Classifier: Programming Language :: Python :: 3
Requires-Python: >=3.8
